HISTORY.rst
README.rst
setup.py
get_text/__init__.py
get_text/cli.py
get_text.egg-info/PKG-INFO
get_text.egg-info/SOURCES.txt
get_text.egg-info/dependency_links.txt
get_text.egg-info/entry_points.txt
get_text.egg-info/not-zip-safe
get_text.egg-info/requires.txt
get_text.egg-info/top_level.txt
get_text/core/__init__.py
get_text/core/decomposes.py
get_text/core/get_article.py
get_text/core/config/__init__.py
get_text/core/config/config.py
get_text/core/config/template.py
get_text/helper/__init__.py
get_text/helper/settings.py
get_text/helper/url_convertor.py