Metadata-Version: 1.1
Name: get-text
Version: 0.1.1
Summary: Test loader with news sites
Home-page: https://github.com/NMelis/get_text
Author: Melis
Author-email: melis.zhoroev+python@gmail.com
License: MIT license
Keywords: get_text
Platform: UNKNOWN
Classifier: Development Status :: 2 - Pre-Alpha
Classifier: Intended Audience :: Developers
Classifier: License :: OSI Approved :: MIT License
Classifier: Natural Language :: Russian
Classifier: Programming Language :: Python :: 2.7
Classifier: Programming Language :: Python :: 3
Classifier: Programming Language :: Python :: 3.4
Classifier: Programming Language :: Python :: 3.5
Classifier: Programming Language :: Python :: 3.6
Classifier: Programming Language :: Python :: 3.7
